Workbook

Sheet SUMMARY
A1: TEST CASE SPECIFICATION — SUMMARY
A3: Project Name | B3: Integrated Coding Education & Competitive Programming Platform
A4: Prepared By | B4: Team 2 - SE20A11
A5: Date | B5: 46204
A6: Version | B6: 2
A7: Total Modules | B7: 15
A8: Total Test Cases | B8: 129
A9: Total Entities | B9: 42
A11: Module | B11: Total Test Cases | C11: High | D11: Medium | E11: Low | F11: Passed | G11: Failed | H11: Pass Rate
A12: AUTH | B12: 2 | C12: 2 | D12: 0 | E12: 0 | F12: =COUNTIF(AUTH!H3:H4, "Pass") | G12: =COUNTIF(AUTH!H3:H4, "Fail") | H12: =F12/B12
A13: USER | B13: 12 | C13: 6 | D13: 3 | E13: 3 | F13: =COUNTIF(USER!H3:H14, "Pass") | G13: =COUNTIF(USER!H3:H14, "Fail") | H13: =F13/B13
A14: ADMIN | B14: 18 | C14: 8 | D14: 10 | E14: 0 | F14: =COUNTIF(ADMIN!H3:H20, "Pass") | G14: =COUNTIF(ADMIN!H3:H20, "Fail") | H14: =F14/B14
A15: CART | B15: 4 | C15: 4 | D15: 0 | E15: 0 | F15: =COUNTIF(CART!H3:H6, "Pass") | G15: =COUNTIF(CART!H3:H6, "Fail") | H15: =F15/B15
A16: CATEGORY | B16: 1 | C16: 1 | D16: 0 | E16: 0 | F16: =COUNTIF(CATEGORY!H3:H3, "Pass") | G16: =COUNTIF(CATEGORY!H3:H3, "Fail") | H16: =F16/B16
A17: PAYMENT | B17: 8 | C17: 5 | D17: 3 | E17: 0 | F17: =COUNTIF(PAYMENT!H3:H10, "Pass") | G17: =COUNTIF(PAYMENT!H3:H10, "Fail") | H17: =F17/B17
A18: COURSE | B18: 11 | C18: 5 | D18: 6 | E18: 0 | F18: =COUNTIF(COURSE!H3:H13, "Pass") | G18: =COUNTIF(COURSE!H3:H13, "Fail") | H18: =F18/B18
A19: QUIZ | B19: 4 | C19: 4 | D19: 0 | E19: 0 | F19: =COUNTIF(QUIZ!H3:H6, "Pass") | G19: =COUNTIF(QUIZ!H3:H6, "Fail") | H19: =F19/B19
A20: INSTRUCTOR | B20: 16 | C20: 9 | D20: 6 | E20: 1 | F20: =COUNTIF(INSTRUCTOR!H3:H18, "Pass") | G20: =COUNTIF(INSTRUCTOR!H3:H18, "Fail") | H20: =F20/B20
A21: AI | B21: 5 | C21: 3 | D21: 2 | E21: 0 | F21: =COUNTIF(AI!H3:H7, "Pass") | G21: =COUNTIF(AI!H3:H7, "Fail") | H21: =F21/B21
A22: JUDGE0 | B22: 2 | C22: 2 | D22: 0 | E22: 0 | F22: =COUNTIF(JUDGE0!H3:H4, "Pass") | G22: =COUNTIF(JUDGE0!H3:H4, "Fail") | H22: =F22/B22
A23: MODERATION | B23: 3 | C23: 2 | D23: 1 | E23: 0 | F23: =COUNTIF(MODERATION!H3:H5, "Pass") | G23: =COUNTIF(MODERATION!H3:H5, "Fail") | H23: =F23/B23
A24: RANKING | B24: 2 | C24: 2 | D24: 0 | E24: 0 | F24: =COUNTIF(RANKING!H3:H4, "Pass") | G24: =COUNTIF(RANKING!H3:H4, "Fail") | H24: =F24/B24
A25: PROBLEM | B25: 19 | C25: 10 | D25: 7 | E25: 2 | F25: =COUNTIF(PROBLEM!H3:H21, "Pass") | G25: =COUNTIF(PROBLEM!H3:H21, "Fail") | H25: =F25/B25
A26: CONTEST | B26: 22 | C26: 13 | D26: 7 | E26: 2 | F26: =COUNTIF(CONTEST!H3:H24, "Pass") | G26: =COUNTIF(CONTEST!H3:H24, "Fail") | H26: =F26/B26
A27: TOTAL | B27: =SUM(B12:B26) | C27: =SUM(C12:C26) | D27: =SUM(D12:D26) | E27: =SUM(E12:E26) | F27: =SUM(F12:F26) | G27: =SUM(G12:G26) | H27: =F27/B27

Sheet AUTH
A1: AUTH MODULE — Test Case Specification
A2: Test Case ID | B2: Function Name | C2: Test Objective | D2: Pre-conditions | E2: Test Steps | F2: Expected Result | G2: Actual Result | H2: Status | I2: Priority
A3: TC_AUTH_01 | B3: Login | C3: Verify that a registered user can log in with valid credentials and receive authentication tokens | D3: 1. A valid user account (username: `john_doe`) exists in the system with status `ACTIVE`. 2. The user's password is correctly hashed and stored in the database. | E3: 1. Navigate to the Login page. 2. Enter a valid username and correct password. 3. Click the "Login" button. 4. Observe the system response and check for session tokens. | F3: - The system returns HTTP 200 OK. - An access token and a refresh token are issued and set as HTTP-only cookies. - The user is redirected to the home/dashboard page. | G3: As expected: The system returns HTTP 200 OK. - An access token and a refresh token are issued and set as HTTP-only cookies. - The user is redirected to the home/dashboard page. | H3: Pass | I3: High
A4: TC_AUTH_02 | B4: Register | C4: Verify that a new user can create an account with valid, unique credentials | D4: 1. The username and email address to be registered do not already exist in the system. | E4: 1. Navigate to the Registration page. 2. Enter a unique username, a valid email, and a strong password. 3. Click the "Register" button. 4. Observe the system response. | F4: - The system returns HTTP 200 OK. - A success message "Register account successfully" is displayed. - A new user record is created in the database with status `ACTIVE`. | G4: As expected: The system returns HTTP 200 OK. - A success message "Register account successfully" is displayed. - A new user record is created in the database with status `ACTIVE`. | H4: Pass | I4: High

Sheet USER
A1: USER MODULE — Test Case Specification
A2: Test Case ID | B2: Function Name | C2: Test Objective | D2: Pre-conditions | E2: Test Steps | F2: Expected Result | G2: Actual Result | H2: Status | I2: Priority
A3: TC_USER_01 | B3: Get All Users (Admin) | C3: Verify that an Administrator can view the complete list of all registered users | D3: 1. The actor is logged in with the `ADMIN` role. 2. At least one user account exists in the system. | E3: 1. Log in as an Administrator. 2. Navigate to the User Management section. 3. Request the full user list. | F3: - The system returns HTTP 200 OK. - A complete list of all user accounts is returned, including their username, email, status, and registration date. | G3: As expected: The system returns HTTP 200 OK. - A complete list of all user accounts is returned, including their username, email, status, and registration date. | H3: Pass | I3: High
A4: TC_USER_02 | B4: Lock/Unlock User (Admin) | C4: Verify that an Administrator can lock a user account and provide a reason | D4: 1. The actor is logged in with the `ADMIN` role. 2. The target user account (ID: 100) exists and has status `ACTIVE`. | E4: 1. Log in as an Administrator. 2. Navigate to the User Management section. 3. Select the target user. 4. Submit a lock action with the reason "Violated community guidelines". 5. Observe the updated user status. | F4: - The system returns HTTP 200 OK. - The target user's status is updated to `LOCKED`. - The `lockReason` field is saved as "Violated community guidelines". - The user can no longer log in. | G4: As expected: The system returns HTTP 200 OK. - The target user's status is updated to `LOCKED`. - The `lockReason` field is saved as "Violated community guidelines". - The user can no longer log in. | H4: Pass | I4: High
A5: TC_USER_03 | B5: Get Dashboard Stats (No Auth) | C5: Verify that the dashboard stats endpoint is accessible without authentication and returns a default empty response | D5: 1. The actor is not logged in (unauthenticated/guest user). | E5: 1. Send a request to the dashboard stats endpoint without any authentication token. | F5: - The system returns HTTP 200 OK. - The response body contains stat fields initialized to default/zero values (no user-specific data is exposed). | G5: As expected: The system returns HTTP 200 OK. - The response body contains stat fields initialized to default/zero values (no user-specific data is exposed). | H5: Pass | I5: Medium
A6: TC_USER_04 | B6: Get Dashboard Stats (Authenticated) | C6: Verify that an authenticated user can retrieve their personalized dashboard statistics | D6: 1. The actor is logged in as a regular User. 2. The user has at least some activity history (submissions, enrollments). | E6: 1. Log in as a User. 2. Navigate to the personal Dashboard page. | F6: - The system returns HTTP 200 OK. - The response message is "Get dashboard stats successfully". - The response payload contains the user's actual statistics (e.g., problems solved, enrolled courses, streak). | G6: As expected: The system returns HTTP 200 OK. - The response message is "Get dashboard stats successfully". - The response payload contains the user's actual statistics (e.g., problems solved, enrolled courses, streak). | H6: Pass | I6: Medium
A7: TC_USER_05 | B7: Get User Activities (Valid Year) | C7: Verify that a user can retrieve their daily coding activity heatmap for a specific year | D7: 1. The actor is logged in as a regular User. 2. The user has daily activity records for the year 2026. | E7: 1. Log in as a User. 2. Navigate to the Activity section and provide the year `2026` as a filter. | F7: - The system returns HTTP 200 OK. - The response message is "Get user activities successfully". - The response contains a list of daily activity entries for the specified year. | G7: As expected: The system returns HTTP 200 OK. - The response message is "Get user activities successfully". - The response contains a list of daily activity entries for the specified year. | H7: Pass | I7: Medium
A8: TC_USER_06 | B8: Get User Activities (Missing Year) | C8: Verify that the system returns an error when the required `year` parameter is missing | D8: 1. The actor is logged in as a regular User. | E8: 1. Log in as a User. 2. Send a request to the activities endpoint without providing the `year` query parameter. | F8: - The system returns HTTP 500 Internal Server Error. - The error indicates a missing required request parameter. - No user data is returned. | G8: As expected: The system returns HTTP 500 Internal Server Error. - The error indicates a missing required request parameter. - No user data is returned. | H8: Pass | I8: Low
A9: TC_USER_07 | B9: Get Enrolled Courses (Authenticated) | C9: Verify that a logged-in user can retrieve their list of enrolled courses | D9: 1. The actor is logged in as a regular User. 2. The user is enrolled in at least one course. | E9: 1. Log in as a User. 2. Navigate to the "My Courses" or enrolled courses section. | F9: - The system returns HTTP 200 OK. - The response message is "Get enrolled courses successfully". - The `result` array contains the list of courses the user is enrolled in, with course title, status, and progress. | G9: As expected: The system returns HTTP 200 OK. - The response message is "Get enrolled courses successfully". - The `result` array contains the list of courses the user is enrolled in, with course title, status, and progress. | H9: Pass | I9: High
A10: TC_USER_08 | B10: Get Enrolled Courses (Anonymous) | C10: Verify that the enrolled courses endpoint returns an empty list for anonymous (unauthenticated) users | D10: 1. The actor is not logged in (guest user). | E10: 1. Without logging in, send a request to the enrolled courses endpoint. | F10: - The system returns HTTP 200 OK. - The `result` array is empty, as no user context is available. - No error or unauthorized response is returned. | G10: As expected: The system returns HTTP 200 OK. - The `result` array is empty, as no user context is available. - No error or unauthorized response is returned. | H10: Pass | I10: Low
A11: TC_USER_09 | B11: Get Submission Statistics (Authenticated) | C11: Verify that a logged-in user can retrieve their coding submission statistics | D11: 1. The actor is logged in as a regular User. 2. The user has submitted at least one code solution. | E11: 1. Log in as a User. 2. Navigate to the Submission Statistics section. | F11: - The system returns HTTP 200 OK. - The response message is "Get submission statistics successfully". - The payload contains `totalSubmissions`, `totalAccepted`, and acceptance rate. | G11: As expected: The system returns HTTP 200 OK. - The response message is "Get submission statistics successfully". - The payload contains `totalSubmissions`, `totalAccepted`, and acceptance rate. | H11: Pass | I11: High
A12: TC_USER_10 | B12: Get Submission Statistics (Anonymous) | C12: Verify that the submission statistics endpoint returns zeroed guest stats for unauthenticated users | D12: 1. The actor is not logged in (guest user). | E12: 1. Without logging in, send a request to the submission statistics endpoint. | F12: - The system returns HTTP 200 OK. - The response contains default/zero values (e.g., `totalSubmissions = 0`). - No user-specific data is exposed. | G12: As expected: The system returns HTTP 200 OK. - The response contains default/zero values (e.g., `totalSubmissions = 0`). - No user-specific data is exposed. | H12: Pass | I12: Low
A13: TC_USER_11 | B13: Get My Info | C13: Verify that an authenticated user can retrieve their own profile information | D13: 1. The actor is logged in as a regular User. | E13: 1. Log in as a User. 2. Navigate to the Profile / "My Info" section. | F13: - The system returns HTTP 200 OK. - The response message is "User info retrieved successfully". - The payload contains the user's `displayName`, `email`, `avatarUrl`, and `status`. | G13: As expected: The system returns HTTP 200 OK. - The response message is "User info retrieved successfully". - The payload contains the user's `displayName`, `email`, `avatarUrl`, and `status`. | H13: Pass | I13: High
A14: TC_USER_12 | B14: Change Password | C14: Verify that an authenticated user can successfully change their password using the correct old password | D14: 1. The actor is logged in as a regular User. 2. The user knows their current password. | E14: 1. Log in as a User. 2. Navigate to the Change Password section. 3. Enter the correct old password and a new strong password. 4. Confirm the new password and submit. | F14: - The system returns HTTP 200 OK. - The response message is "Password changed successfully". - The user's password hash is updated in the database. - Future login attempts using the old password will fail. | G14: Failed: The system returns HTTP 200 OK and reports success, but due to session synchronization lag (Redis cache update delay), the old password session remains active and can still be used to log in for up to 15 minutes after the change. | H14: Fail | I14: High

Sheet ADMIN
A1: ADMIN MODULE — Test Case Specification
A2: Test Case ID | B2: Function Name | C2: Test Objective | D2: Pre-conditions | E2: Test Steps | F2: Expected Result | G2: Actual Result | H2: Status | I2: Priority
A3: TC_ADMIN_01 | B3: Get All Courses (Admin) | C3: Verify that an Administrator can view the full list of courses submitted to the platform | D3: 1. The actor is logged in with the `ADMIN` role. 2. At least one course exists in the system. | E3: 1. Log in as an Administrator. 2. Navigate to the Course Management section. | F3: - The system returns HTTP 200 OK. - A list of all courses is returned, including their title, status (DRAFTS, PENDING_ADMIN, APPROVED, REJECTED), instructor name, and chapter count. | G3: As expected: The system returns HTTP 200 OK. - A list of all courses is returned, including their title, status (DRAFTS, PENDING_ADMIN, APPROVED, REJECTED), instructor name, and chapter count. | H3: Pass | I3: High
A4: TC_ADMIN_02 | B4: Approve Course (Valid Status) | C4: Verify that an Administrator can approve a course that is pending review | D4: 1. The actor is logged in with the `ADMIN` role. 2. A target course exists with status `PENDING_ADMIN`. 3. The course has passed the AI moderation check. | E4: 1. Log in as an Administrator. 2. Navigate to the Course Management section. 3. Select the target pending course. 4. Submit an approval with a positive admin note. | F4: - The system returns HTTP 200 OK. - The target course status changes to `APPROVED`. - The admin note is saved against the course record. - The course becomes publicly visible to users. | G4: Failed: The course status successfully changed to APPROVED in the database, but it did not become visible in the public course list due to a missing cache eviction trigger (Redis course list cache not cleared). | H4: Fail | I4: High
A5: TC_ADMIN_03 | B5: Approve Course (Invalid Status) | C5: Verify that the system rejects a course approval request with an invalid status value | D5: 1. The actor is logged in with the `ADMIN` role. 2. A target course exists in the system. | E5: 1. Log in as an Administrator. 2. Navigate to the Course Management section. 3. Submit an approval action with an unrecognized status value (e.g., "INVALID_STATUS"). | F5: - The system returns HTTP 400 Bad Request. - The error code `4000` is returned in the response. - The course status remains unchanged. - An error message indicating the invalid status is returned. | G5: As expected: The system returns HTTP 400 Bad Request. - The error code `4000` is returned in the response. - The course status remains unchanged. - An error message indicating the invalid status is returned. | H5: Pass | I5: High
A6: TC_ADMIN_04 | B6: Get Dashboard Stats (Admin) | C6: Verify that the Admin dashboard displays accurate platform-wide summary statistics | D6: 1. The actor is logged in with the `ADMIN` role. 2. The system has existing data (users, orders, courses). | E6: 1. Log in as an Administrator. 2. Navigate to the Admin Dashboard page. | F6: - The system returns HTTP 200 OK. - The response contains key platform metrics: total registered users, total revenue generated, total active courses, and new registrations. | G6: As expected: The system returns HTTP 200 OK. - The response contains key platform metrics: total registered users, total revenue generated, total active courses, and new registrations. | H6: Pass | I6: Medium
A7: TC_ADMIN_05 | B7: Get Recent Deposits (Admin) | C7: Verify that an Administrator can view the most recent deposit transactions across all users | D7: 1. The actor is logged in with the `ADMIN` role. 2. At least one deposit transaction exists in the system. | E7: 1. Log in as an Administrator. 2. Navigate to the Financial / Recent Deposits section. | F7: - The system returns HTTP 200 OK. - A list of the most recent deposit records is returned, including user name, amount, transaction code, status, and timestamp. | G7: As expected: The system returns HTTP 200 OK. - A list of the most recent deposit records is returned, including user name, amount, transaction code, status, and timestamp. | H7: Pass | I7: Medium
A8: TC_ADMIN_06 | B8: Get Monthly Financial Records | C8: Verify that an Administrator can view month-by-month financial performance data | D8: 1. The actor is logged in with the `ADMIN` role. 2. Order and transaction data spanning multiple months exists. | E8: 1. Log in as an Administrator. 2. Navigate to the Financial Reports > Monthly Records section. | F8: - The system returns HTTP 200 OK. - A breakdown of financial data is returned per month, including total revenue, platform fees, and payout amounts. | G8: As expected: The system returns HTTP 200 OK. - A breakdown of financial data is returned per month, including total revenue, platform fees, and payout amounts. | H8: Pass | I8: High
A9: TC_ADMIN_07 | B9: Get Top Revenue Courses | C9: Verify that an Administrator can identify the highest revenue-generating courses | D9: 1. The actor is logged in with the `ADMIN` role. 2. At least one completed order exists. | E9: 1. Log in as an Administrator. 2. Navigate to the Financial Reports > Top Courses section. | F9: - The system returns HTTP 200 OK. - A ranked list of courses is returned, ordered by total revenue generated, including course title, instructor name, and revenue amount. | G9: As expected: The system returns HTTP 200 OK. - A ranked list of courses is returned, ordered by total revenue generated, including course title, instructor name, and revenue amount. | H9: Pass | I9: High
A10: TC_ADMIN_08 | B10: Get Financial Details | C10: Verify that an Administrator can view the aggregated financial summary of the platform | D10: 1. The actor is logged in with the `ADMIN` role. | E10: 1. Log in as an Administrator. 2. Navigate to the Financial Reports > Details section. | F10: - The system returns HTTP 200 OK. - The response contains aggregate financial figures: total gross revenue, total platform commission, total instructor payout amount. | G10: As expected: The system returns HTTP 200 OK. - The response contains aggregate financial figures: total gross revenue, total platform commission, total instructor payout amount. | H10: Pass | I10: High
A11: TC_ADMIN_09 | B11: Get Orders (Default Pagination) | C11: Verify that an Administrator can view orders using default pagination settings | D11: 1. The actor is logged in with the `ADMIN` role. 2. At least one order exists in the system. | E11: 1. Log in as an Administrator. 2. Navigate to the Order Management section without applying any filters. | F11: - The system returns HTTP 200 OK. - The first page of orders is returned with a default page size (10 records). - Each record includes order ID, user, total amount, status, and date. | G11: As expected: The system returns HTTP 200 OK. - The first page of orders is returned with a default page size (10 records). - Each record includes order ID, user, total amount, status, and date. | H11: Pass | I11: Medium
A12: TC_ADMIN_10 | B12: Get Orders (Date Filter) | C12: Verify that an Administrator can filter orders by a specific date range | D12: 1. The actor is logged in with the `ADMIN` role. 2. Orders exist within the date range being queried. | E12: 1. Log in as an Administrator. 2. Navigate to the Order Management section. 3. Apply a date range filter (e.g., from 2026-01-01 to 2026-07-15) and a specific page/size. | F12: - The system returns HTTP 200 OK. - Only orders created within the specified date range are returned. | G12: As expected: The system returns HTTP 200 OK. - Only orders created within the specified date range are returned. | H12: Pass | I12: Medium
A13: TC_ADMIN_11 | B13: Get Awards (Default Pagination) | C13: Verify that an Administrator can view platform award/prize records with default pagination | D13: 1. The actor is logged in with the `ADMIN` role. | E13: 1. Log in as an Administrator. 2. Navigate to the Financial Reports > Awards section without applying filters. | F13: - The system returns HTTP 200 OK. - The first page of award records is returned with default pagination. | G13: As expected: The system returns HTTP 200 OK. - The first page of award records is returned with default pagination. | H13: Pass | I13: Medium
... A20: TC_ADMIN_18 | B20: Get Instructor Applications (Admin) | C20: Verify that an Administrator can view all instructor applications including AI evaluation results | D20: 1. The actor is logged in with the `ADMIN` role. 2. At least one instructor application exists (status: PENDING, APPROVED, or REJECTED). | E20: 1. Log in as an Administrator. 2. Navigate to the Instructor Applications section. | F20: - The system returns HTTP 200 OK. - A list of all applications is returned, including the applicant's name, AI evaluation score (`aiScore`), AI recommendation, and current status. | G20: As expected: The system returns HTTP 200 OK. - A list of all applications is returned, including the applicant's name, AI evaluation score (`aiScore`), AI recommendation, and current status. | H20: Pass | I20: High

Sheet CART
A1: CART MODULE — Test Case Specification
A2: Test Case ID | B2: Function Name | C2: Test Objective | D2: Pre-conditions | E2: Test Steps | F2: Expected Result | G2: Actual Result | H2: Status | I2: Priority
A3: TC_CART_01 | B3: View Cart | C3: Verify that a logged-in user can view the list of courses currently in their shopping cart | D3: 1. The actor is logged in as a regular User. 2. The user's cart contains at least one course (Course ID: 10). | E3: 1. Log in as a User. 2. Navigate to the Shopping Cart page. | F3: - The system returns HTTP 200 OK. - A list of course IDs (and associated course details) currently in the user's cart is returned. | G3: As expected: The system returns HTTP 200 OK. - A list of course IDs (and associated course details) currently in the user's cart is returned. | H3: Pass | I3: High
A4: TC_CART_02 | B4: Add Course to Cart | C4: Verify that a logged-in user can successfully add a course to their shopping cart | D4: 1. The actor is logged in as a regular User. 2. The target course (ID: 10) exists, is published, and has not already been purchased or added to the cart by this user. | E4: 1. Log in as a User. 2. Browse to a course detail page. 3. Click "Add to Cart" button. | F4: - The system returns HTTP 200 OK. - The success message "Course added to cart successfully" is displayed. - The course now appears in the user's cart. | G4: As expected: The system returns HTTP 200 OK. - The success message "Course added to cart successfully" is displayed. - The course now appears in the user's cart. | H4: Pass | I4: High
A5: TC_CART_03 | B5: Remove Course from Cart | C5: Verify that a logged-in user can remove a specific course from their shopping cart | D5: 1. The actor is logged in as a regular User. 2. The target course (ID: 10) is already present in the user's cart. | E5: 1. Log in as a User. 2. Navigate to the Shopping Cart page. 3. Click "Remove" on the target course. | F5: - The system returns HTTP 200 OK. - The success message "Course removed from cart successfully" is displayed. - The course is no longer present in the user's cart. | G5: As expected: The system returns HTTP 200 OK. - The success message "Course removed from cart successfully" is displayed. - The course is no longer present in the user's cart. | H5: Pass | I5: High
A6: TC_CART_04 | B6: Clear Cart | C6: Verify that a logged-in user can clear all items from their shopping cart at once | D6: 1. The actor is logged in as a regular User. 2. The user's cart contains at least one course item. | E6: 1. Log in as a User. 2. Navigate to the Shopping Cart page. 3. Click "Clear Cart" or "Remove All" button. | F6: - The system returns HTTP 200 OK. - The success message "Cart cleared successfully" is displayed. - The user's cart is now empty. | G6: As expected: The system returns HTTP 200 OK. - The success message "Cart cleared successfully" is displayed. - The user's cart is now empty. | H6: Pass | I6: High

Sheet CATEGORY
A1: CATEGORY MODULE — Test Case Specification
A2: Test Case ID | B2: Function Name | C2: Test Objective | D2: Pre-conditions | E2: Test Steps | F2: Expected Result | G2: Actual Result | H2: Status | I2: Priority
A3: TC_CATEGORY_01 | B3: Get All Categories | C3: Verify that the system returns all available course categories to any visitor without requiring authentication | D3: 1. At least one category record exists in the system. 2. The endpoint is publicly accessible (no authentication required). | E3: 1. Navigate to the Categories section or the course filter page (no login required). 2. Observe the list of categories displayed. | F3: - The system returns HTTP 200 OK. - A complete list of all active categories is returned, each including the category `id`, `name`, and `description`. | G3: As expected: The system returns HTTP 200 OK. - A complete list of all active categories is returned, each including the category `id`, `name`, and `description`. | H3: Pass | I3: High

Sheet PAYMENT
A1: PAYMENT MODULE — Test Case Specification
A2: Test Case ID | B2: Function Name | C2: Test Objective | D2: Pre-conditions | E2: Test Steps | F2: Expected Result | G2: Actual Result | H2: Status | I2: Priority
A3: TC_PAYMENT_01 | B3: Get Wallet Balance | C3: Verify that a logged-in user can view their current wallet balance | D3: 1. The actor is logged in as a regular User. 2. The user has an active wallet with a balance (e.g., 100.50 VND equivalent). | E3: 1. Log in as a User. 2. Navigate to the Wallet section. | F3: - The system returns HTTP 200 OK. - The response contains the user's current wallet balance (e.g., `100.50`). | G3: As expected: The system returns HTTP 200 OK. - The response contains the user's current wallet balance (e.g., `100.50`). | H3: Pass | I3: High
A4: TC_PAYMENT_02 | B4: Create Deposit Request | C4: Verify that a logged-in user can initiate a deposit (top-up) to their wallet via a payment gateway | D4: 1. The actor is logged in as a regular User. 2. The user has an active wallet. 3. The payment gateway (e.g., PayOS) is operational. | E4: 1. Log in as a User. 2. Navigate to the Wallet > Deposit section. 3. Enter the desired deposit amount and confirm. 4. Observe the system response. | F4: - The system returns HTTP 200 OK. - A payment checkout URL (`checkoutUrl`) is returned, which the user can follow to complete the payment. - A unique `transactionCode` is generated and stored with status `PENDING`. | G4: As expected: The system returns HTTP 200 OK. - A payment checkout URL (`checkoutUrl`) is returned, which the user can follow to complete the payment. - A unique `transactionCode` is generated and stored with status `PENDING`. | H4: Pass | I4: High
A5: TC_PAYMENT_03 | B5: Cancel Payment | C5: Verify that a user can cancel a pending payment transaction | D5: 1. The actor is logged in as a regular User. 2. A payment transaction with the given transaction code exists with status `PENDING`. | E5: 1. Log in as a User. 2. Navigate to the Transaction History section. 3. Select the pending transaction and click "Cancel". | F5: - The system returns HTTP 200 OK. - The response message is "Payment cancelled successfully". - The transaction status is updated to `CANCELLED`. - The wallet balance remains unchanged. | G5: As expected: The system returns HTTP 200 OK. - The response message is "Payment cancelled successfully". - The transaction status is updated to `CANCELLED`. - The wallet balance remains unchanged. | H5: Pass | I5: High
A6: TC_PAYMENT_04 | B6: Handle Payment Webhook | C6: Verify that the system correctly processes a successful payment notification from the payment gateway | D6: 1. A pending payment transaction exists in the system with a matching transaction code. 2. The payment gateway sends a webhook callback with a success code (`"00"`). | E6: 1. The payment gateway sends a POST request to the webhook endpoint with a success payload. 2. Observe the system's processing behavior. | F6: - The system returns HTTP 200 with `success = true`. - The corresponding payment transaction status is updated to `SUCCESS`. - The user's wallet balance is credited with the deposited amount. | G6: Failed: The system returns HTTP 200 with success = true, and the payment transaction status is updated to SUCCESS. However, the user's wallet balance was not credited because of a database lock timeout on the Wallet entity during concurrent requests (race condition). | H6: Fail | I6: High
A7: TC_PAYMENT_05 | B7: Checkout (Order from Cart) | C7: Verify that a logged-in user can place an order for courses currently in their cart | D7: 1. The actor is logged in as a regular User. 2. The user's cart contains at least two courses (IDs: 1, 2). 3. The user's wallet has sufficient balance to cover the total order amount. | E7: 1. Log in as a User. 2. Navigate to the Shopping Cart. 3. Review items and click "Checkout". 4. Confirm the purchase. | F7: - The system returns HTTP 200 OK. - The response message is "Order checkout completed successfully". - A new Order record is created with status `COMPLETED`. - The user is automatically enrolled in all purchased courses. - The corresponding amount is deducted from the user's wallet. | G7: As expected: The system returns HTTP 200 OK. - The response message is "Order checkout completed successfully". - A new Order record is created with status `COMPLETED`. - The user is automatically enrolled in all purchased courses. - The corresponding amount is deducted from the user's wallet. | H7: Pass | I7: High
A8: TC_PAYMENT_06 | B8: Get Purchase History | C8: Verify that a logged-in user can view a paginated list of their completed orders | D8: 1. The actor is logged in as a regular User. 2. The user has at least one completed order. | E8: 1. Log in as a User. 2. Navigate to the Purchase History section. 3. Observe the default first page (page=0, size=10). | F8: - The system returns HTTP 200 OK. - The response message is "Fetched purchase history successfully". - A paginated list of completed orders is returned, including order date, total amount, and course names. | G8: As expected: The system returns HTTP 200 OK. - The response message is "Fetched purchase history successfully". - A paginated list of completed orders is returned, including order date, total amount, and course names. | H8: Pass | I8: Medium
A9: TC_PAYMENT_07 | B9: Get Wallet Transactions | C9: Verify that a logged-in user can view a paginated history of their wallet balance changes (top-ups and deductions) | D9: 1. The actor is logged in as a regular User. 2. The user has at least one wallet transaction (deposit or deduction). | E9: 1. Log in as a User. 2. Navigate to the Wallet > Transaction History section. | F9: - The system returns HTTP 200 OK. - The response message is "Get wallet transaction statistics successfully". - A paginated list of wallet transactions is returned, with type (ADD/DEDUCT), amount, status, and date. | G9: As expected: The system returns HTTP 200 OK. - The response message is "Get wallet transaction statistics successfully". - A paginated list of wallet transactions is returned, with type (ADD/DEDUCT), amount, status, and date. | H9: Pass | I9: Medium
A10: TC_PAYMENT_08 | B10: Get Payment Transactions | C10: Verify that a logged-in user can view a paginated history of their direct payment (deposit) transactions | D10: 1. The actor is logged in as a regular User. 2. The user has made at least one deposit via the payment gateway. | E10: 1. Log in as a User. 2. Navigate to the Wallet > Deposit History section. | F10: - The system returns HTTP 200 OK. - The response message is "Get payment transaction statistics successfully". - A paginated list of deposit transactions is returned, including transaction code, amount, status, and date. | G10: As expected: The system returns HTTP 200 OK. - The response message is "Get payment transaction statistics successfully". - A paginated list of deposit transactions is returned, including transaction code, amount, status, and date. | H10: Pass | I10: Medium

Sheet COURSE
A1: COURSE MODULE — Test Case Specification
A2: Test Case ID | B2: Function Name | C2: Test Objective | D2: Pre-conditions | E2: Test Steps | F2: Expected Result | G2: Actual Result | H2: Status | I2: Priority
A3: TC_COURSE_01 | B3: Get Public Course List | C3: Verify that a user can browse the paginated list of all published courses on the platform | D3: 1. The actor is logged in as a regular User. 2. At least one course with status `APPROVED` exists. | E3: 1. Log in as a User. 2. Navigate to the Course Catalog / Browse Courses page. | F3: - The system returns HTTP 200 OK. - A paginated list of approved courses is returned, each including title, thumbnail, instructor name, average rating, price, and total enrollments. | G3: As expected: The system returns HTTP 200 OK. - A paginated list of approved courses is returned, each including title, thumbnail, instructor name, average rating, price, and total enrollments. | H3: Pass | I3: High
A4: TC_COURSE_02 | B4: Get Course Detail | C4: Verify that a user can view the full detail page of a specific course | D4: 1. The actor is logged in as a regular User. 2. The target course (ID: 1) exists with status `APPROVED`. | E4: 1. Log in as a User. 2. Browse to a specific course and click on it. | F4: - The system returns HTTP 200 OK. - The full course detail is returned, including description, what-you-will-learn, prerequisites, instructor profile, total lessons, and price. | G4: As expected: The system returns HTTP 200 OK. - The full course detail is returned, including description, what-you-will-learn, prerequisites, instructor profile, total lessons, and price. | H4: Pass | I4: High
A5: TC_COURSE_03 | B5: Get Course Curriculum | C5: Verify that a user can view the chapter and lesson structure of a course before enrolling | D5: 1. The actor is logged in as a regular User. 2. The target course (ID: 1) is approved and has at least one chapter with lessons. | E5: 1. Log in as a User. 2. Navigate to the course detail page. 3. Scroll to or click the "Curriculum" tab. | F5: - The system returns HTTP 200 OK. - A structured list of chapters is returned, each containing its lesson titles, types (video/quiz/problem), and duration. | G5: As expected: The system returns HTTP 200 OK. - A structured list of chapters is returned, each containing its lesson titles, types (video/quiz/problem), and duration. | H5: Pass | I5: Medium
A6: TC_COURSE_04 | B6: Get Course Reviews | C6: Verify that a user can view ratings and reviews submitted for a course | D6: 1. The actor is logged in as a regular User. 2. The target course (ID: 1) has at least one review. | E6: 1. Log in as a User. 2. Navigate to the course detail page. 3. Click the "Reviews" tab. | F6: - The system returns HTTP 200 OK. - The response includes the overall `averageRating`, `totalReviews` count, and a list of individual user reviews with star rating and comment content. | G6: As expected: The system returns HTTP 200 OK. - The response includes the overall `averageRating`, `totalReviews` count, and a list of individual user reviews with star rating and comment content. | H6: Pass | I6: Medium
A7: TC_COURSE_05 | B7: Submit Course Review | C7: Verify that an enrolled user can submit a star rating and written review for a course they have access to | D7: 1. The actor is logged in as a regular User. 2. The user is enrolled in the target course (ID: 1). | E7: 1. Log in as a User. 2. Navigate to the course page for an enrolled course. 3. Go to the Reviews tab. 4. Select a star rating (e.g., 5 stars) and write a comment. 5. Submit the review. | F7: - The system returns HTTP 200 OK. - The response message is "Review submitted successfully". - The new review is saved to the database and the course's `averageRating` and `totalReviews` are recalculated. | G7: Failed: The review is saved successfully, but the course's averageRating was not recalculated because the asynchronous recalculation task failed with a NullPointerException in RatingService.java line 112 when handling zero-star review inputs. | H7: Fail | I7: High
A8: TC_COURSE_06 | B8: Get Learning Detail | C8: Verify that an enrolled user can access the learning-specific details of their course | D8: 1. The actor is logged in as a regular User. 2. The user is actively enrolled in the target course (enrollment status: `ACTIVE`). | E8: 1. Log in as a User. 2. Navigate to "My Courses" and select an enrolled course. 3. Enter the learning view. | F8: - The system returns HTTP 200 OK. - The response contains the course's learning-specific data including the user's overall progress percentage. | G8: As expected: The system returns HTTP 200 OK. - The response contains the course's learning-specific data including the user's overall progress percentage. | H8: Pass | I8: Medium
A9: TC_COURSE_07 | B9: Get Learning Curriculum (with Progress) | C9: Verify that an enrolled user can see the course curriculum with their completion progress tracked | D9: 1. The actor is logged in as a regular User. 2. The user is enrolled and has completed at least one lesson. | E9: 1. Log in as a User. 2. Navigate to the course learning view. 3. View the curriculum panel. | F9: - The system returns HTTP 200 OK. - The curriculum is returned with each lesson marked as either "completed" or "not completed" based on the user's actual progress. | G9: As expected: The system returns HTTP 200 OK. - The curriculum is returned with each lesson marked as either "completed" or "not completed" based on the user's actual progress. | H9: Pass | I9: Medium
A10: TC_COURSE_08 | B10: Get Lesson Detail (Learning) | C10: Verify that an enrolled user can open and view the content of a specific lesson | D10: 1. The actor is logged in as a regular User. 2. The user is enrolled in the course containing the target lesson (Lesson ID: 200). 3. The lesson status is `ACTIVE`. | E10: 1. Log in as a User. 2. Navigate to the course learning view. 3. Click on a specific lesson from the curriculum. | F10: - The system returns HTTP 200 OK. - The lesson detail is returned, including the lesson title, theory content (HTML), video URL, and any associated coding problems. | G10: As expected: The system returns HTTP 200 OK. - The lesson detail is returned, including the lesson title, theory content (HTML), video URL, and any associated coding problems. | H10: Pass | I10: High
A11: TC_COURSE_09 | B11: Get Lesson Comments | C11: Verify that a user can view the Q&A discussion thread for a specific lesson | D11: 1. The actor is logged in as a regular User. 2. The target lesson (ID: 200) has at least one comment or reply. | E11: 1. Log in as a User. 2. Navigate to a lesson's learning page. 3. Scroll to or click the "Comments / Q&A" section. | F11: - The system returns HTTP 200 OK. - A list of root-level comments is returned, with each comment also containing its nested replies. | G11: As expected: The system returns HTTP 200 OK. - A list of root-level comments is returned, with each comment also containing its nested replies. | H11: Pass | I11: Medium
A12: TC_COURSE_10 | B12: Add Lesson Comment | C12: Verify that an enrolled user can post a comment in the Q&A section of a lesson | D12: 1. The actor is logged in as a regular User. 2. The user is enrolled in the course containing the target lesson (ID: 200). | E12: 1. Log in as a User. 2. Navigate to a lesson's Q&A section. 3. Type a comment in the input box. 4. Click "Post" or "Submit". | F12: - The system returns HTTP 200 OK. - The response message is "Comment posted successfully". - The new comment appears in the lesson's Q&A thread. | G12: As expected: The system returns HTTP 200 OK. - The response message is "Comment posted successfully". - The new comment appears in the lesson's Q&A thread. | H12: Pass | I12: Medium
A13: TC_COURSE_11 | B13: Complete Lesson | C13: Verify that an enrolled user can mark a lesson as completed, and the system updates their progress | D13: 1. The actor is logged in as a regular User. 2. The user is enrolled in the course (ID: 1) and has not yet completed the target lesson (ID: 200). | E13: 1. Log in as a User. 2. Navigate to the lesson learning page. 3. Finish watching the video or reading the content. 4. Click "Mark as Complete" or complete the lesson interaction. | F13: - The system returns HTTP 200 OK. - The response message is "Lesson completed successfully". - A `LessonProgress` record is created for the user and lesson. - The `completedLessonsCount` for the user in this course is incremented. | G13: As expected: The system returns HTTP 200 OK. - The response message is "Lesson completed successfully". - A `LessonProgress` record is created for the user and lesson. - The `completedLessonsCount` for the user in this course is incremented. | H13: Pass | I13: High

Sheet QUIZ
A1: QUIZ MODULE — Test Case Specification
A2: Test Case ID | B2: Function Name | C2: Test Objective | D2: Pre-conditions | E2: Test Steps | F2: Expected Result | G2: Actual Result | H2: Status | I2: Priority
A3: TC_QUIZ_01 | B3: Get Quiz Details (Authenticated) | C3: Verify that an enrolled user can access and view the quiz associated with a specific lesson | D3: 1. The actor is logged in as a regular User. 2. The user is enrolled in the course containing the target lesson (ID: 10). 3. The lesson has an associated quiz. | E3: 1. Log in as a User. 2. Navigate to the lesson learning page that contains a quiz. 3. Click "Take Quiz" or navigate to the quiz tab. | F3: - The system returns HTTP 200 OK. - The response message is "Get quiz details successfully". - The quiz content is returned, including the quiz title and all questions with their shuffled answer options (correct answer is not marked). | G3: As expected: The system returns HTTP 200 OK. - The response message is "Get quiz details successfully". - The quiz content is returned, including the quiz title and all questions with their shuffled answer options (correct answer is not marked). | H3: Pass | I3: High
A4: TC_QUIZ_02 | B4: Get Quiz Details (Unauthenticated) | C4: Verify that the system denies access to quiz content for users who are not logged in | D4: 1. The actor is not logged in (guest user). 2. A quiz exists for the target lesson (ID: 10). | E4: 1. Without logging in, attempt to access a lesson's quiz page. | F4: - The system returns HTTP 401 Unauthorized. - No quiz content is returned. - The user is redirected to the login page. | G4: As expected: The system returns HTTP 401 Unauthorized. - No quiz content is returned. - The user is redirected to the login page. | H4: Pass | I4: High
A5: TC_QUIZ_03 | B5: Submit Quiz Answers (Authenticated) | C5: Verify that an enrolled user can submit their answers for a quiz and receive a score | D5: 1. The actor is logged in as a regular User. 2. The user is enrolled in the course and the quiz (ID: 20) is accessible. 3. The user has not yet submitted this quiz (or re-attempt is allowed). | E5: 1. Log in as a User. 2. Navigate to the quiz. 3. Answer all questions (or leave some blank). 4. Click "Submit Quiz". | F5: - The system returns HTTP 200 OK. - The response message is "Submit quiz successfully". - A `QuizAttempt` record is saved, storing the user's score and all submitted answers. - The final score and correct/incorrect breakdown are returned. | G5: Failed: The quiz submission returns HTTP 500 Internal Server Error instead of 200 OK because the system attempts to save a null score value in the QuizAttempt database record when a student submits an incomplete or empty quiz form. | H5: Fail | I5: High
A6: TC_QUIZ_04 | B6: Submit Quiz Answers (Unauthenticated) | C6: Verify that the system denies quiz submission for users who are not logged in | D6: 1. The actor is not logged in (guest user). | E6: 1. Without logging in, attempt to submit answers to a quiz. | F6: - The system returns HTTP 401 Unauthorized. - No quiz attempt is recorded. - The user is redirected to the login page. | G6: As expected: The system returns HTTP 401 Unauthorized. - No quiz attempt is recorded. - The user is redirected to the login page. | H6: Pass | I6: High

Sheet INSTRUCTOR
A1: INSTRUCTOR MODULE — Test Case Specification
A2: Test Case ID | B2: Function Name | C2: Test Objective | D2: Pre-conditions | E2: Test Steps | F2: Expected Result | G2: Actual Result | H2: Status | I2: Priority
A3: TC_INSTRUCTOR_01 | B3: Apply to Become Instructor | C3: Verify that an authenticated user can submit an application to become a course instructor on the platform | D3: 1. The actor is logged in as a regular User. 2. The user has not previously submitted an instructor application. 3. The user has a CV to upload and a valid introduction text. | E3: 1. Log in as a User. 2. Navigate to the "Become an Instructor" section. 3. Fill in the required fields: full name, major, bio, and upload a CV. 4. Submit the application. | F3: - The system returns HTTP 200 OK. - The application is saved to the database with status `PENDING`. - The AI evaluation pipeline is triggered to score the CV and introduction. - The user receives a confirmation that their application is under review. | G3: As expected: The system returns HTTP 200 OK. - The application is saved to the database with status `PENDING`. - The AI evaluation pipeline is triggered to score the CV and introduction. - The user receives a confirmation that their application is under review. | H3: Pass | I3: High
A4: TC_INSTRUCTOR_02 | B4: Get My Application Status | C4: Verify that an applicant can check the current status of their instructor application | D4: 1. The actor is logged in as a regular User. 2. The user has previously submitted an instructor application. | E4: 1. Log in as a User. 2. Navigate to the "My Application Status" section. | F4: - The system returns HTTP 200 OK. - The current application status is returned (e.g., `PENDING`, `APPROVED`, or `REJECTED`). - If available, the AI evaluation score and admin note are also included. | G4: As expected: The system returns HTTP 200 OK. - The current application status is returned (e.g., `PENDING`, `APPROVED`, or `REJECTED`). - If available, the AI evaluation score and admin note are also included. | H4: Pass | I4: Medium
A5: TC_INSTRUCTOR_03 | B5: Get Instructor's Own Courses | C5: Verify that an approved Instructor can view the list of all courses they have created | D5: 1. The actor is logged in with the `INSTRUCTOR` role. 2. The instructor has created at least one course. | E5: 1. Log in as an Instructor. 2. Navigate to the Instructor Dashboard > My Courses section. | F5: - The system returns HTTP 200 OK. - The response message is "Fetched instructor courses successfully". - A list of all courses owned by the instructor is returned, including title, status, total enrollments, and average rating. | G5: As expected: The system returns HTTP 200 OK. - The response message is "Fetched instructor courses successfully". - A list of all courses owned by the instructor is returned, including title, status, total enrollments, and average rating. | H5: Pass | I5: High
A6: TC_INSTRUCTOR_04 | B6: Create New Course | C6: Verify that an approved Instructor can create a new course draft on the platform | D6: 1. The actor is logged in with the `INSTRUCTOR` role. | E6: 1. Log in as an Instructor. 2. Navigate to Instructor Dashboard > Create New Course. 3. Fill in the required course information (title, short description, price, category, type). 4. Save the course. | F6: - The system returns HTTP 200 OK. - The response message is "Course created successfully". - A new course record is created in the database with status `DRAFTS` and linked to the instructor. | G6: As expected: The system returns HTTP 200 OK. - The response message is "Course created successfully". - A new course record is created in the database with status `DRAFTS` and linked to the instructor. | H6: Pass | I6: High
A7: TC_INSTRUCTOR_05 | B7: Upload Media File | C7: Verify that an Instructor can upload image or video media files for use in their course content | D7: 1. The actor is logged in with the `INSTRUCTOR` role. 2. A valid media file (image/video) is available for upload. 3. The Cloudinary media storage service is operational. | E7: 1. Log in as an Instructor. 2. Navigate to the course editor or media upload section. 3. Select and upload a file (e.g., thumbnail image). | F7: - The system returns HTTP 200 OK. - The response message is "File uploaded successfully". - A secure URL (`secureUrl`) pointing to the uploaded file on Cloudinary is returned and can be used in the course content. | G7: As expected: The system returns HTTP 200 OK. - The response message is "File uploaded successfully". - A secure URL (`secureUrl`) pointing to the uploaded file on Cloudinary is returned and can be used in the course content. | H7: Pass | I7: High
A8: TC_INSTRUCTOR_06 | B8: Get Course Detail (Instructor View) | C8: Verify that an Instructor can view the full editable detail of one of their own courses | D8: 1. The actor is logged in with the `INSTRUCTOR` role. 2. The target course (ID: 100) exists and belongs to this instructor. | E8: 1. Log in as an Instructor. 2. Navigate to My Courses. 3. Click on the target course to open its details. | F8: - The system returns HTTP 200 OK. - The response message is "Fetched instructor course detail successfully". - The full course detail is returned including all chapters, lessons, and current status. | G8: As expected: The system returns HTTP 200 OK. - The response message is "Fetched instructor course detail successfully". - The full course detail is returned including all chapters, lessons, and current status. | H8: Pass | I8: High
A9: TC_INSTRUCTOR_07 | B9: Update Course Draft | C9: Verify that an Instructor can edit and save changes to a course that is in draft status | D9: 1. The actor is logged in with the `INSTRUCTOR` role. 2. The target course (ID: 100) belongs to this instructor and has status `DRAFTS`. | E9: 1. Log in as an Instructor. 2. Navigate to the course editor for the target course. 3. Modify the course title, description, or other fields. 4. Click "Save Draft". | F9: - The system returns HTTP 200 OK. - The response message is "Course draft saved successfully." - The updated fields are persisted in the database. | G9: As expected: The system returns HTTP 200 OK. - The response message is "Course draft saved successfully." - The updated fields are persisted in the database. | H9: Pass | I9: High
A10: TC_INSTRUCTOR_08 | B10: Generate Testcases via AI | C10: Verify that an Instructor can use the AI-powered tool to auto-generate testcases for a coding problem in their course | D10: 1. The actor is logged in with the `INSTRUCTOR` role. 2. The Gemini AI service is operational. | E10: 1. Log in as an Instructor. 2. Navigate to the Testcase Generator tool. 3. Provide a problem description and a sample solution code. 4. Click "Generate". | F10: - The system returns HTTP 200 OK. - The response message is "Testcases generated successfully." - A list of generated testcase pairs (input data and expected output) is returned. | G10: Failed: The system returns HTTP 500 Internal Server Error (Gemini API quota exceeded or connection timeout). No testcases are generated or returned. | H10: Fail | I10: Medium
A11: TC_INSTRUCTOR_09 | B11: Submit Course for Review | C11: Verify that an Instructor can submit a completed draft course to the Admin review queue | D11: 1. The actor is logged in with the `INSTRUCTOR` role. 2. The target course (ID: 100) belongs to this instructor, has status `DRAFTS`, and has at least one active lesson. | E11: 1. Log in as an Instructor. 2. Navigate to the course editor. 3. Verify all content is complete. 4. Click "Submit for Review". | F11: - The system returns HTTP 200 OK. - The response message is "Course submitted for review successfully". - The course status is updated to `PENDING_AI` (then transitions to `PENDING_ADMIN` after passing AI moderation). - All lessons are set to `ACTIVE` status. | G11: As expected: The system returns HTTP 200 OK. - The response message is "Course submitted for review successfully". - The course status is updated to `PENDING_AI` (then transitions to `PENDING_ADMIN` after passing AI moderation). - All lessons are set to `ACTIVE` status. | H11: Pass | I11: High
A12: TC_INSTRUCTOR_10 | B12: Get Course Statistics | C12: Verify that an Instructor can view performance analytics for one of their published courses | D12: 1. The actor is logged in with the `INSTRUCTOR` role. 2. The target course (ID: 100) is published and has at least one enrolled student. | E12: 1. Log in as an Instructor. 2. Navigate to the course detail page. 3. Click the "Statistics" or "Analytics" tab. | F12: - The system returns HTTP 200 OK. - The response message is "Fetched course statistics successfully". - The analytics data includes total enrollments, average rating, completion rate (%), and revenue generated. | G12: As expected: The system returns HTTP 200 OK. - The response message is "Fetched course statistics successfully". - The analytics data includes total enrollments, average rating, completion rate (%), and revenue generated. | H12: Pass | I12: Medium
A13: TC_INSTRUCTOR_11 | B13: Get Revenue Summary | C13: Verify that an Instructor can view a financial summary of their total earnings for a selected time period | D13: 1. The actor is logged in with the `INSTRUCTOR` role. 2. The instructor has at least one completed order from their courses in the selected period. | E13: 1. Log in as an Instructor. 2. Navigate to the Revenue Dashboard. 3. Select a time period filter (e.g., "This Month"). | F13: - The system returns HTTP 200 OK. - The response includes: total gross revenue, platform commission fee deducted, and the instructor's net payout amount for the period. | G13: As expected: The system returns HTTP 200 OK. - The response includes: total gross revenue, platform commission fee deducted, and the instructor's net payout amount for the period. | H13: Pass | I13: High
... A18: TC_INSTRUCTOR_16 | B18: Submit Payout Request | C18: Verify that an Instructor with sufficient accumulated earnings can request a withdrawal to their bank account | D18: 1. The actor is logged in with the `INSTRUCTOR` role. 2. The instructor's available earnings balance is sufficient to cover the requested payout amount. 3. The instructor has not submitted a duplicate payout request for the same period. | E18: 1. Log in as an Instructor. 2. Navigate to Revenue > Request Payout. 3. Enter the desired amount, bank name, bank account number, and account holder name. 4. Confirm and submit. | F18: - The system returns HTTP 200 OK. - A new `PayoutRequest` record is created in the database with status `PENDING`. - The request is queued for Admin review and approval. | G18: As expected: The system returns HTTP 200 OK. - A new `PayoutRequest` record is created in the database with status `PENDING`. - The request is queued for Admin review and approval. | H18: Pass | I18: High

Sheet AI
A1: AI MODULE — Test Case Specification
A2: Test Case ID | B2: Function Name | C2: Test Objective | D2: Pre-conditions | E2: Test Steps | F2: Expected Result | G2: Actual Result | H2: Status | I2: Priority
A3: TC_AI_01 | B3: Generate Visualizer (Cache Hit) | C3: Verify that the system immediately returns a previously generated AI visualizer from cache without re-generating | D3: 1. The actor is logged in as a regular User. 2. An AI-generated visualizer already exists in the cache for the target problem (Problem ID: `prob123`). | E3: 1. Log in as a User. 2. Navigate to the problem page for a problem that has a cached visualizer. 3. Trigger the visualizer generation (without forcing re-generation). | F3: - The system returns HTTP 200 OK. - The response message is "Success (from cache)". - The cached visualizer data is returned immediately without triggering an AI generation job. - `fromCache = true` in the response. | G3: As expected: The system returns HTTP 200 OK. - The response message is "Success (from cache)". - The cached visualizer data is returned immediately without triggering an AI generation job. - `fromCache = true` in the response. | H3: Pass | I3: High
A4: TC_AI_02 | B4: Generate Visualizer (Cache Miss, Async) | C4: Verify that the system initiates an asynchronous AI generation job when no cached visualizer exists | D4: 1. The actor is logged in as a regular User. 2. No cached visualizer exists for the target problem. | E4: 1. Log in as a User. 2. Navigate to a problem page that has no cached visualizer. 3. Trigger the visualizer generation. | F4: - The system returns HTTP 202 Accepted. - A `jobId` is returned so the client can poll for status. - `fromCache = false` in the response. - A background AI generation job is started using the Gemini API. | G4: Failed: The background job fails to start and throws a standard HTTP 500. The Gemini API client raised a standard connection error: 'Connection aborted: RemoteDisconnected'. | H4: Fail | I4: High
A5: TC_AI_03 | B5: Check Visualization Job Status | C5: Verify that a user can check the processing status of an in-progress AI visualization job | D5: 1. The actor is logged in as a regular User. 2. A valid async job ID (e.g., `job123`) has been returned from a previous generate request. | E5: 1. Log in as a User. 2. Use the `jobId` to query the job status endpoint. | F5: - The system returns HTTP 200 OK. - The response contains the current job status (`PENDING`, `COMPLETED`, or `FAILED`) and, if completed, the resulting visualizer data. | G5: As expected: The system returns HTTP 200 OK. - The response contains the current job status (`PENDING`, `COMPLETED`, or `FAILED`) and, if completed, the resulting visualizer data. | H5: Pass | I5: High
A6: TC_AI_04 | B6: Get Cached Visualizer (Exists) | C6: Verify that a user can directly retrieve an existing cached visualizer for a specific problem | D6: 1. The actor is logged in as a regular User. 2. A cached visualizer record exists for the target problem (`prob123`). | E6: 1. Log in as a User. 2. Request the cached visualizer directly using the problem ID. | F6: - The system returns HTTP 200 OK. - The full cached visualizer data is returned, including the animation steps and explanation generated by AI. | G6: As expected: The system returns HTTP 200 OK. - The full cached visualizer data is returned, including the animation steps and explanation generated by AI. | H6: Pass | I6: Medium
A7: TC_AI_05 | B7: Get Cached Visualizer (Not Found) | C7: Verify that the system returns a clear "not found" message when no cached visualizer exists for a problem | D7: 1. The actor is logged in as a regular User. 2. No cached visualizer record exists for the target problem. | E7: 1. Log in as a User. 2. Request the cached visualizer for a problem that has not been generated yet. | F7: - The system returns HTTP 200 OK. - The response message is "No cache found", informing the client to trigger a generation request instead. | G7: As expected: The system returns HTTP 200 OK. - The response message is "No cache found", informing the client to trigger a generation request instead. | H7: Pass | I7: Medium

Sheet JUDGE0
A1: JUDGE0 MODULE — Test Case Specification
A2: Test Case ID | B2: Function Name | C2: Test Objective | D2: Pre-conditions | E2: Test Steps | F2: Expected Result | G2: Actual Result | H2: Status | I2: Priority
A3: TC_JUDGE0_01 | B3: Submit Code for Evaluation | C3: Verify that a user can submit their source code solution to be judged against the problem's testcases | D3: 1. The actor is logged in as a regular User. 2. The target problem (ID: 1) is active and has at least one testcase. 3. The Judge0 code execution service is operational. | E3: 1. Log in as a User. 2. Navigate to a problem page. 3. Write a solution in the code editor. 4. Select the programming language (e.g., Python 3). 5. Click "Submit". | F3: - The system returns HTTP 200 OK. - A `submissionId` is returned. - A `ProblemSubmission` record is created in the database with initial `verdict = PENDING`. - The source code is sent to the Judge0 service for async evaluation. | G3: Failed: The system returns HTTP 504 Gateway Timeout because the Judge0 execution service was down or unresponsive, causing the submission record to stay permanently stuck in PENDING status. | H3: Fail | I3: High
A4: TC_JUDGE0_02 | B4: Process Judge0 Callback (Accepted) | C4: Verify that the system correctly updates a submission's verdict when the Judge0 service sends back an "Accepted" result | D4: 1. A `ProblemSubmission` record exists with `verdict = PENDING`. 2. The Judge0 service has finished evaluating the code and sends a callback to the system's webhook endpoint. | E4: 1. Judge0 finishes evaluating the code submission. 2. Judge0 sends a PUT request (callback) to the system containing the submission token, verdict (Accepted), execution time, and memory used. | F4: - The system returns HTTP 200 OK. - The `ProblemSubmission` record is updated: `verdict = ACCEPTED`, `executionTime` and `memoryUsed` are saved. - The problem's `totalAccepted` counter is incremented. - The user's score is updated accordingly. | G4: As expected: The system returns HTTP 200 OK. - The `ProblemSubmission` record is updated: `verdict = ACCEPTED`, `executionTime` and `memoryUsed` are saved. - The problem's `totalAccepted` counter is incremented. - The user's score is updated accordingly. | H4: Pass | I4: High

Sheet MODERATION
A1: MODERATION MODULE — Test Case Specification
A2: Test Case ID | B2: Function Name | C2: Test Objective | D2: Pre-conditions | E2: Test Steps | F2: Expected Result | G2: Actual Result | H2: Status | I2: Priority
A3: TC_MODERATION_01 | B3: Trigger AI Course Moderation | C3: Verify that an Administrator can manually trigger the AI content moderation pipeline for a specific course | D3: 1. The actor is logged in with the `ADMIN` role. 2. The target course (ID: 1) exists in the system and has content (lessons, descriptions). 3. The RabbitMQ message broker is running and the AI moderation consumer is active. | E3: 1. Log in as an Administrator. 2. Navigate to the Course Management section and select the target course. 3. Click "Trigger AI Moderation". | F3: - The system returns HTTP 200 OK. - A moderation message is published to the RabbitMQ queue. - The AI moderation pipeline picks up the message and begins evaluating the course content. - A confirmation response is returned indicating the job was queued. | G3: As expected: The system returns HTTP 200 OK. - A moderation message is published to the RabbitMQ queue. - The AI moderation pipeline picks up the message and begins evaluating the course content. - A confirmation response is returned indicating the job was queued. | H3: Pass | I3: High
A4: TC_MODERATION_02 | B4: Get Moderation Report (Exists) | C4: Verify that an Administrator can view the AI-generated moderation report for a course that has completed evaluation | D4: 1. The actor is logged in with the `ADMIN` role. 2. The target course (ID: 1) has been evaluated by the AI pipeline and a `CourseModerationReport` record exists with status `APPROVED`. | E4: 1. Log in as an Administrator. 2. Navigate to the course detail or moderation section. 3. Request the moderation report for the target course. | F4: - The system returns HTTP 200 OK. - The full moderation report is returned, including the overall status (APPROVED/REJECTED), AI evaluation score, specific content flags, and the detailed `reportJson`. | G4: Failed: The system returns HTTP 500 Internal Server Error because of a JSON parsing exception while mapping the reportJson column to the Java ModerationReportEntity class. | H4: Fail | I4: High
A5: TC_MODERATION_03 | B5: Get Moderation Report (Not Found) | C5: Verify that the system returns a clear "not found" error when no moderation report exists for a course | D5: 1. The actor is logged in with the `ADMIN` role. 2. The target course (ID: 99) exists but has NOT yet been submitted for AI moderation (no report record exists). | E5: 1. Log in as an Administrator. 2. Attempt to view the moderation report for a course that has not been evaluated yet. | F5: - The system returns HTTP 404 Not Found. - An error message is returned indicating that no moderation report exists for the specified course. - No report data is returned. | G5: As expected: The system returns HTTP 404 Not Found. - An error message is returned indicating that no moderation report exists for the specified course. - No report data is returned. | H5: Pass | I5: Medium

Sheet RANKING
A1: RANKING MODULE — Test Case Specification
A2: Test Case ID | B2: Function Name | C2: Test Objective | D2: Pre-conditions | E2: Test Steps | F2: Expected Result | G2: Actual Result | H2: Status | I2: Priority
A3: TC_RANKING_01 | B3: Get Global Leaderboard | C3: Verify that a logged-in user can view the global ranking leaderboard of all users on the platform | D3: 1. The actor is logged in as a regular User. 2. At least a few user accounts have a non-zero `score` from solving coding problems. | E3: 1. Log in as a User. 2. Navigate to the Leaderboard or Rankings page. | F3: - The system returns HTTP 200 OK. - An ordered list of top-ranked users is returned, sorted by score in descending order. Each entry includes the user's rank number, display name, avatar, and total score. | G3: As expected: The system returns HTTP 200 OK. - An ordered list of top-ranked users is returned, sorted by score in descending order. Each entry includes the user's rank number, display name, avatar, and total score. | H3: Pass | I3: High
A4: TC_RANKING_02 | B4: Get My Personal Ranking Stats | C4: Verify that a logged-in user can view their own rank position and score relative to other users | D4: 1. The actor is logged in as a regular User. 2. The user has at least one accepted code submission contributing to their score. | E4: 1. Log in as a User. 2. Navigate to the Rankings page. 3. View the "My Stats" or personal ranking section. | F4: - The system returns HTTP 200 OK. - The user's personal ranking data is returned, including their current rank position, total score, and how many points they need to reach the next rank tier (`pointsToNextRank`). | G4: As expected: The system returns HTTP 200 OK. - The user's personal ranking data is returned, including their current rank position, total score, and how many points they need to reach the next rank tier (`pointsToNextRank`). | H4: Pass | I4: High

Sheet PROBLEM
A1: PROBLEM MODULE — Test Case Specification
A2: Test Case ID | B2: Function Name | C2: Test Objective | D2: Pre-conditions | E2: Test Steps | F2: Expected Result | G2: Actual Result | H2: Status | I2: Priority
A3: TC_PROBLEM_01 | B3: Get All Problems (Admin) | C3: Verify that an Administrator can view the full list of all coding problems in the system, including inactive ones | D3: 1. The actor is logged in with the `ADMIN` role. 2. At least one problem exists in the system. | E3: 1. Log in as an Administrator. 2. Navigate to the Problem Management section. | F3: - The system returns HTTP 200 OK. - A complete list of all problems is returned, including their title, difficulty, scope (PUBLIC/PRIVATE/COURSE), active status, and total submission count. | G3: As expected: The system returns HTTP 200 OK. - A complete list of all problems is returned, including their title, difficulty, scope (PUBLIC/PRIVATE/COURSE), active status, and total submission count. | H3: Pass | I3: High
A4: TC_PROBLEM_02 | B4: Get All Problem Tags (Admin) | C4: Verify that an Administrator can view all existing problem classification tags | D4: 1. The actor is logged in with the `ADMIN` role. 2. At least one tag exists (e.g., "Dynamic Programming"). | E4: 1. Log in as an Administrator. 2. Navigate to Problem Management > Tags. | F4: - The system returns HTTP 200 OK. - A list of all problem tags is returned, each including the tag name and URL-friendly slug. | G4: As expected: The system returns HTTP 200 OK. - A list of all problem tags is returned, each including the tag name and URL-friendly slug. | H4: Pass | I4: Medium
A5: TC_PROBLEM_03 | B5: Create New Problem (Admin) | C5: Verify that an Administrator can create a new coding problem with an initial version | D5: 1. The actor is logged in with the `ADMIN` role. | E5: 1. Log in as an Administrator. 2. Navigate to Problem Management > Create New Problem. 3. Fill in problem title, description, difficulty level, time/memory limits, and assign tags. 4. Save the problem. | F5: - The system returns HTTP 200 OK. - A new `Problem` record and its initial `ProblemVersion` (version 1) are created in the database. - The problem is created with `isActive = false` until testcases are uploaded and the problem is activated. | G5: As expected: The system returns HTTP 200 OK. - A new `Problem` record and its initial `ProblemVersion` (version 1) are created in the database. - The problem is created with `isActive = false` until testcases are uploaded and the problem is activated. | H5: Pass | I5: High
A6: TC_PROBLEM_04 | B6: Update Problem (Admin) | C6: Verify that an Administrator can edit and update the content of an existing problem, creating a new version snapshot | D6: 1. The actor is logged in with the `ADMIN` role. 2. The target problem (ID: 1) exists with at least one version. | E6: 1. Log in as an Administrator. 2. Navigate to the target problem in Problem Management. 3. Modify the description, constraints, examples, or difficulty. 4. Save the changes. | F6: - The system returns HTTP 200 OK. - A new `ProblemVersion` record is created with an incremented version number (e.g., version 2). - The old version is preserved for rollback purposes. - The new version becomes the active version. | G6: Failed: The new version is created in the database, but the system failed to set it as the active version. Regular users are still served the old version of the problem because the activeVersionId column on the parent Problem entity was not updated. | H6: Fail | I6: High
A7: TC_PROBLEM_05 | B7: Delete (Soft-Delete) Problem (Admin) | C7: Verify that an Administrator can soft-delete a problem, making it invisible to users without permanently removing data | D7: 1. The actor is logged in with the `ADMIN` role. 2. The target problem (ID: 1) exists. | E7: 1. Log in as an Administrator. 2. Navigate to the target problem. 3. Click "Delete" or "Deactivate". | F7: - The system returns HTTP 200 OK. - The problem's `isActive` flag is set to `false`. - The problem no longer appears in the public problem list. - All historical submission data for this problem is preserved. | G7: As expected: The system returns HTTP 200 OK. - The problem's `isActive` flag is set to `false`. - The problem no longer appears in the public problem list. - All historical submission data for this problem is preserved. | H7: Pass | I7: Medium
A8: TC_PROBLEM_06 | B8: Update Problem Scope (Admin) | C8: Verify that an Administrator can change the visibility scope of a problem | D8: 1. The actor is logged in with the `ADMIN` role. 2. The target problem (ID: 1) currently has scope `PRIVATE`. | E8: 1. Log in as an Administrator. 2. Select the target problem. 3. Change the problem scope to `PUBLIC`. 4. Save. | F8: - The system returns HTTP 200 OK. - The `problemScope` of the problem (and its active version) is updated to `PUBLIC`. - The problem now appears in the public problem list for all users. | G8: As expected: The system returns HTTP 200 OK. - The `problemScope` of the problem (and its active version) is updated to `PUBLIC`. - The problem now appears in the public problem list for all users. | H8: Pass | I8: High
A9: TC_PROBLEM_07 | B9: Toggle Problem Public Status (Admin) | C9: Verify that an Administrator can show or hide a problem from the public problem list | D9: 1. The actor is logged in with the `ADMIN` role. 2. The target problem (ID: 1) currently has `isPublic = false`. | E9: 1. Log in as an Administrator. 2. Select the target problem. 3. Toggle the "Public" switch to ON. | F9: - The system returns HTTP 200 OK. - The `isPublic` flag is updated to `true`. - The problem becomes visible in the public problem catalog. | G9: As expected: The system returns HTTP 200 OK. - The `isPublic` flag is updated to `true`. - The problem becomes visible in the public problem catalog. | H9: Pass | I9: Medium
A10: TC_PROBLEM_08 | B10: Rollback Problem Version (Admin) | C10: Verify that an Administrator can revert a problem to a previous content version | D10: 1. The actor is logged in with the `ADMIN` role. 2. The target problem (ID: 1) has at least 3 versions stored. 3. Version 3 is currently active; the Administrator wants to revert to version 2. | E10: 1. Log in as an Administrator. 2. Navigate to the target problem's Version History. 3. Select version 2 and click "Rollback to this version". | F10: - The system returns HTTP 200 OK. - Version 2 is now the active version for the problem. - Version 3 remains in the version history but is no longer active. - Existing submissions are still linked to their original submission version. | G10: As expected: The system returns HTTP 200 OK. - Version 2 is now the active version for the problem. - Version 3 remains in the version history but is no longer active. - Existing submissions are still linked to their original submission version. | H10: Pass | I10: Low
A11: TC_PROBLEM_09 | B11: Activate Problem (Admin) | C11: Verify that an Administrator can activate a problem after its testcases have been validated and uploaded | D11: 1. The actor is logged in with the `ADMIN` role. 2. The target problem (ID: 1) exists with `isActive = false`. 3. Testcases have been successfully uploaded and validated. | E11: 1. Log in as an Administrator. 2. Navigate to the target problem. 3. Click "Activate" and confirm the total testcase count (e.g., 10). | F11: - The system returns HTTP 200 OK. - The problem's `isActive` flag is set to `true` and `totalTestcase` is set to 10. - The problem is now available for users to solve. | G11: As expected: The system returns HTTP 200 OK. - The problem's `isActive` flag is set to `true` and `totalTestcase` is set to 10. - The problem is now available for users to solve. | H11: Pass | I11: High
A12: TC_PROBLEM_10 | B12: Get Problem Testcases (Admin) | C12: Verify that an Administrator can view the complete list of testcases for a specific problem | D12: 1. The actor is logged in with the `ADMIN` role. 2. The target problem (ID: 1) has at least one testcase stored. | E12: 1. Log in as an Administrator. 2. Navigate to the target problem. 3. Click the "Testcases" tab. | F12: - The system returns HTTP 200 OK. - All testcases are returned in order, each showing the `inputData` and `expectedOutput`. | G12: As expected: The system returns HTTP 200 OK. - All testcases are returned in order, each showing the `inputData` and `expectedOutput`. | H12: Pass | I12: Medium
A13: TC_PROBLEM_11 | B13: Save/Replace Problem Testcases (Admin) | C13: Verify that an Administrator can upload and save a new set of testcases for a problem | D13: 1. The actor is logged in with the `ADMIN` role. 2. The target problem (ID: 1) exists. 3. A valid list of testcase pairs (input/output) is prepared. | E13: 1. Log in as an Administrator. 2. Navigate to the problem's Testcases section. 3. Upload or paste the new testcase pairs. 4. Click "Save Testcases". | F13: - The system returns HTTP 200 OK. - The new testcases are saved to the database linked to the current active problem version. - Old testcases are replaced by the new ones. | G13: As expected: The system returns HTTP 200 OK. - The new testcases are saved to the database linked to the current active problem version. - Old testcases are replaced by the new ones. | H13: Pass | I13: High
... A21: TC_PROBLEM_19 | B21: Get User's Submission History | C21: Verify that a user can view all of their past code submissions for a specific problem | D21: 1. The actor is logged in as a regular User. 2. The user has submitted at least one solution to the target problem (ID: 1). | E21: 1. Log in as a User. 2. Navigate to the problem page. 3. Click the "Submissions" tab. | F21: - The system returns HTTP 200 OK. - A list of the user's past submissions is returned in reverse chronological order, including: submission date, programming language used, verdict (ACCEPTED/WRONG_ANSWER/etc.), and execution time. | G21: As expected: The system returns HTTP 200 OK. - A list of the user's past submissions is returned in reverse chronological order, including: submission date, programming language used, verdict (ACCEPTED/WRONG_ANSWER/etc.), and execution time. | H21: Pass | I21: High

Sheet CONTEST
A1: CONTEST MODULE — Test Case Specification
A2: Test Case ID | B2: Function Name | C2: Test Objective | D2: Pre-conditions | E2: Test Steps | F2: Expected Result | G2: Actual Result | H2: Status | I2: Priority
A3: TC_CONTEST_01 | B3: Get All Contests (Admin) | C3: Verify that an Administrator can view the complete list of all contests regardless of their status | D3: 1. The actor is logged in with the `ADMIN` role. 2. At least one contest exists in the system. | E3: 1. Log in as an Administrator. 2. Navigate to the Contest Management section. | F3: - The system returns HTTP 200 OK. - A list of all contests is returned, including their title, scoring rule, start/end time, participant count, and current status (DRAFT/PUBLISHED/CANCELLED). | G3: As expected: The system returns HTTP 200 OK. - A list of all contests is returned, including their title, scoring rule, start/end time, participant count, and current status (DRAFT/PUBLISHED/CANCELLED). | H3: Pass | I3: High
A4: TC_CONTEST_02 | B4: Create New Contest (Admin) | C4: Verify that an Administrator can create a new coding contest | D4: 1. The actor is logged in with the `ADMIN` role. | E4: 1. Log in as an Administrator. 2. Navigate to Contest Management > Create Contest. 3. Fill in the contest title, scoring rule (ICPC), start time, end time, and description. 4. Save the contest. | F4: - The system returns HTTP 200 OK. - A new `Contest` record is created in the database with status `DRAFT`. - The contest is not yet visible to regular users until it is published. | G4: As expected: The system returns HTTP 200 OK. - A new `Contest` record is created in the database with status `DRAFT`. - The contest is not yet visible to regular users until it is published. | H4: Pass | I4: High
A5: TC_CONTEST_03 | B5: Get Contest Detail (Admin) | C5: Verify that an Administrator can view the full detail of a specific contest | D5: 1. The actor is logged in with the `ADMIN` role. 2. The target contest (ID: 1) exists. | E5: 1. Log in as an Administrator. 2. Navigate to Contest Management and select the target contest. | F5: - The system returns HTTP 200 OK. - Full contest details are returned, including title, description, scoring rule, timing, status, and the list of assigned problems. | G5: As expected: The system returns HTTP 200 OK. - Full contest details are returned, including title, description, scoring rule, timing, status, and the list of assigned problems. | H5: Pass | I5: Medium
A6: TC_CONTEST_04 | B6: Update Contest (Admin) | C6: Verify that an Administrator can edit the details of an existing contest | D6: 1. The actor is logged in with the `ADMIN` role. 2. The target contest (ID: 1) exists and is in `DRAFT` status. | E6: 1. Log in as an Administrator. 2. Select the target contest. 3. Modify the title, time, or description. 4. Save the changes. | F6: - The system returns HTTP 200 OK. - The contest record is updated in the database with the new information. | G6: As expected: The system returns HTTP 200 OK. - The contest record is updated in the database with the new information. | H6: Pass | I6: High
A7: TC_CONTEST_05 | B7: Soft-Delete Contest (Admin) | C7: Verify that an Administrator can cancel a contest, preventing further registrations | D7: 1. The actor is logged in with the `ADMIN` role. 2. The target contest (ID: 1) is in `DRAFT` or `PUBLISHED` status. | E7: 1. Log in as an Administrator. 2. Select the target contest. 3. Click "Cancel" or "Delete". | F7: - The system returns HTTP 200 OK. - The contest status is updated to `CANCELLED`. - The contest is no longer visible to new participants, but historical data is preserved. | G7: As expected: The system returns HTTP 200 OK. - The contest status is updated to `CANCELLED`. - The contest is no longer visible to new participants, but historical data is preserved. | H7: Pass | I7: Medium
A8: TC_CONTEST_06 | B8: Publish Contest (Admin) | C8: Verify that an Administrator can publish a draft contest, making it visible and open for user registration | D8: 1. The actor is logged in with the `ADMIN` role. 2. The target contest (ID: 1) is in `DRAFT` status and has at least one problem assigned. | E8: 1. Log in as an Administrator. 2. Select the target draft contest. 3. Click "Publish". | F8: - The system returns HTTP 200 OK. - The contest status is updated to `PUBLISHED`. - The contest becomes visible in the public contest list and users can now register. | G8: As expected: The system returns HTTP 200 OK. - The contest status is updated to `PUBLISHED`. - The contest becomes visible in the public contest list and users can now register. | H8: Pass | I8: High
A9: TC_CONTEST_07 | B9: Restore Cancelled Contest (Admin) | C9: Verify that an Administrator can restore a cancelled contest back to draft status for re-editing | D9: 1. The actor is logged in with the `ADMIN` role. 2. The target contest (ID: 1) is in `CANCELLED` status. | E9: 1. Log in as an Administrator. 2. Navigate to the cancelled contest. 3. Click "Restore". | F9: - The system returns HTTP 200 OK. - The contest status is reverted to `DRAFT`. - The contest can be edited and re-published by the admin. | G9: As expected: The system returns HTTP 200 OK. - The contest status is reverted to `DRAFT`. - The contest can be edited and re-published by the admin. | H9: Pass | I9: Medium
A10: TC_CONTEST_08 | B10: Permanently Delete Contest (Admin) | C10: Verify that an Administrator can permanently remove a contest and all its associated data from the system | D10: 1. The actor is logged in with the `ADMIN` role. 2. The target contest (ID: 1) exists (typically in CANCELLED or DRAFT status). | E10: 1. Log in as an Administrator. 2. Navigate to the target contest. 3. Click "Permanently Delete" and confirm the action. | F10: - The system returns HTTP 200 OK. - The contest record and all related data (participants, rankings, problem assignments) are permanently deleted from the database. | G10: As expected: The system returns HTTP 200 OK. - The contest record and all related data (participants, rankings, problem assignments) are permanently deleted from the database. | H10: Pass | I10: Low
A11: TC_CONTEST_09 | B11: Get Contest Problems (Admin) | C11: Verify that an Administrator can view the list of problems assigned to a specific contest | D11: 1. The actor is logged in with the `ADMIN` role. 2. The target contest (ID: 1) has at least one problem assigned. | E11: 1. Log in as an Administrator. 2. Navigate to the contest detail page. 3. View the Problems tab. | F11: - The system returns HTTP 200 OK. - The list of problems assigned to the contest is returned, ordered by `orderIndex`, each showing the problem title and difficulty. | G11: As expected: The system returns HTTP 200 OK. - The list of problems assigned to the contest is returned, ordered by `orderIndex`, each showing the problem title and difficulty. | H11: Pass | I11: Medium
A12: TC_CONTEST_10 | B12: Add Problem to Contest (Admin) | C12: Verify that an Administrator can assign a coding problem to a specific contest | D12: 1. The actor is logged in with the `ADMIN` role. 2. The target contest (ID: 1) exists. 3. The target problem (ID: 5) exists, is active, and is not already assigned to this contest. | E12: 1. Log in as an Administrator. 2. Navigate to the contest's Problems section. 3. Click "Add Problem", search and select the target problem, and assign an order index. | F12: - The system returns HTTP 200 OK. - The problem is successfully linked to the contest. - The problem now appears in the contest's problem list. | G12: Failed: The system returns HTTP 400 Bad Request: "Problem is already assigned to another active contest". However, the problem is not in any active contest; a soft-deleted contest mapping was incorrectly included in the active check query. | H12: Fail | I12: High
A13: TC_CONTEST_11 | B13: Remove Problem from Contest (Admin) | C13: Verify that an Administrator can remove a problem from a contest | D13: 1. The actor is logged in with the `ADMIN` role. 2. The target problem (ID: 5) is currently assigned to the target contest (ID: 1). | E13: 1. Log in as an Administrator. 2. Navigate to the contest's Problems section. 3. Click "Remove" on the target problem. | F13: - The system returns HTTP 200 OK. - The problem is unlinked from the contest. - The problem no longer appears in the contest's problem list. | G13: As expected: The system returns HTTP 200 OK. - The problem is unlinked from the contest. - The problem no longer appears in the contest's problem list. | H13: Pass | I13: High
... A24: TC_CONTEST_22 | B24: Get Contest Submissions | C24: Verify that a user can view the history of code submissions made during a specific contest | D24: 1. The actor is logged in as a regular User or Administrator. 2. The target contest (ID: 1) has at least one submission. | E24: 1. Log in as a User or Admin. 2. Navigate to the contest page. 3. View the Submissions tab. | F24: - The system returns HTTP 200 OK. - A list of submissions for the contest is returned, each showing the problem name, verdict, language used, submitted at time, and (if the contest is over) the user's display name. | G24: As expected: The system returns HTTP 200 OK. - A list of submissions for the contest is returned, each showing the problem name, verdict, language used, submitted at time, and (if the contest is over) the user's display name. | H24: Pass | I24: High
